alibabacloud_cloudauth20201112/__init__.py
alibabacloud_cloudauth20201112/client.py
alibabacloud_cloudauth20201112/models.py
alibabacloud_cloudauth20201112_py2-1.0.1.dist-info/LICENSE
alibabacloud_cloudauth20201112_py2-1.0.1.dist-info/METADATA
alibabacloud_cloudauth20201112_py2-1.0.1.dist-info/WHEEL
alibabacloud_cloudauth20201112_py2-1.0.1.dist-info/top_level.txt
alibabacloud_cloudauth20201112_py2-1.0.1.dist-info/RECORD
